mutemplate/__init__.py
mutemplate/__main__.py
mutemplate/compiler.py
mutemplate/mutemplate.py
mutemplate/watcher.py
mutemplate-1.7.dist-info/METADATA
mutemplate-1.7.dist-info/WHEEL
mutemplate-1.7.dist-info/entry_points.txt
mutemplate-1.7.dist-info/top_level.txt
mutemplate-1.7.dist-info/RECORD
