Metadata-Version: 2.4
Name: mutemplate
Version: 1.7
Summary: Compile template files into a standalone python file
Author-email: Mark Blakeney <mark.blakeney@bullet-systems.net>
License-Expression: GPL-3.0-or-later
Project-URL: Homepage, https://github.com/bulletmark/mutemplate
Keywords: micropython,microdot,utemplate
Classifier: Programming Language :: Python :: 3
Requires-Python: >=3.7
